README.md
setup.py
hypothesis_pb.egg-info/PKG-INFO
hypothesis_pb.egg-info/SOURCES.txt
hypothesis_pb.egg-info/dependency_links.txt
hypothesis_pb.egg-info/requires.txt
hypothesis_pb.egg-info/top_level.txt
hypothesis_protobuf/__init__.py
hypothesis_protobuf/module_conversion.py
hypothesis_protobuf/utils.py