Metadata-Version: 1.1
Name: hypothesis-pb
Version: 1.1.0
Summary: Hypothesis extension to allow generating protobuf messages matching a schema.
Home-page: https://github.com/CurataEng/hypothesis-protobuf
Author: Curata Inc.
Author-email: eng@curata.com
License: MIT
Platform: any
Classifier: Programming Language :: Python
Classifier: Programming Language :: Python :: 2
Classifier: Programming Language :: Python :: 2.7
Classifier: Programming Language :: Python :: 3
Classifier: Programming Language :: Python :: 3.6
Classifier: Topic :: Software Development :: Libraries :: Python Modules
Classifier: Intended Audience :: Developers
Classifier: Operating System :: OS Independent
Classifier: License :: OSI Approved :: MIT License
